indexable_generator/__init__.py
indexable_generator-1.0.1.dist-info/LICENSE
indexable_generator-1.0.1.dist-info/METADATA
indexable_generator-1.0.1.dist-info/NOTICE
indexable_generator-1.0.1.dist-info/WHEEL
indexable_generator-1.0.1.dist-info/top_level.txt
indexable_generator-1.0.1.dist-info/RECORD
